llama_index/program/lmformatenforcer/__init__.py
llama_index/program/lmformatenforcer/base.py
llama_index/program/lmformatenforcer/utils.py
llama_index_program_lmformatenforcer-0.4.1.dist-info/METADATA
llama_index_program_lmformatenforcer-0.4.1.dist-info/WHEEL
llama_index_program_lmformatenforcer-0.4.1.dist-info/licenses/LICENSE
llama_index_program_lmformatenforcer-0.4.1.dist-info/RECORD
