Metadata-Version: 2.4
Name: llama-index-program-lmformatenforcer
Version: 0.4.1
Summary: llama-index program lmformatenforcer integration
Author-email: Your Name <you@example.com>
License-Expression: MIT
License-File: LICENSE
Requires-Python: <4.0,>=3.9
Requires-Dist: llama-index-core<0.15,>=0.13.0
Requires-Dist: llama-index-llms-huggingface<0.7,>=0.6.0
Requires-Dist: llama-index-llms-llama-cpp<0.6,>=0.5.0
